evo/objects/__init__.py
evo/objects/_model_config.py
evo/objects/data.py
evo/objects/exceptions.py
evo/objects/io.py
evo/objects/py.typed
evo/objects/client/__init__.py
evo/objects/client/api_client.py
evo/objects/client/object_client.py
evo/objects/client/parse.py
evo/objects/endpoints/__init__.py
evo/objects/endpoints/models.py
evo/objects/endpoints/api/__init__.py
evo/objects/endpoints/api/data_api.py
evo/objects/endpoints/api/metadata_api.py
evo/objects/endpoints/api/objects_api.py
evo/objects/endpoints/api/stages_api.py
evo/objects/parquet/__init__.py
evo/objects/parquet/loader.py
evo/objects/parquet/types.py
evo/objects/utils/__init__.py
evo/objects/utils/data.py
evo/objects/utils/table_formats.py
evo/objects/utils/tables.py
evo_objects-0.3.3.dist-info/METADATA
evo_objects-0.3.3.dist-info/WHEEL
evo_objects-0.3.3.dist-info/licenses/LICENSE.md
evo_objects-0.3.3.dist-info/RECORD
