Metadata-Version: 2.4
Name: evo-objects
Version: 0.3.3
Summary: Python SDK for using the Seequent Evo Geoscience Object API
Project-URL: Source, https://github.com/SeequentEvo/evo-python-sdk
Project-URL: Tracker, https://github.com/SeequentEvo/evo-python-sdk/issues
Project-URL: Homepage, https://www.seequent.com/
Project-URL: Documentation, https://developer.seequent.com/
Author-email: Seequent <support@seequent.com>
License-File: LICENSE.md
Requires-Python: >=3.10
Requires-Dist: evo-sdk-common[jmespath]>=0.5.8
Requires-Dist: pydantic<3,>=2
Provides-Extra: aiohttp
Requires-Dist: evo-sdk-common[aiohttp]; extra == 'aiohttp'
Provides-Extra: notebooks
Requires-Dist: evo-sdk-common[notebooks]; extra == 'notebooks'
Provides-Extra: utils
Requires-Dist: numpy; extra == 'utils'
Requires-Dist: pandas; extra == 'utils'
Requires-Dist: pyarrow; extra == 'utils'
Requires-Dist: pyarrow-stubs; extra == 'utils'
